Topsis/__init__.py
Topsis/__main__.py
Topsis_saksham_102103521-1.1.0.dist-info/LICENSE
Topsis_saksham_102103521-1.1.0.dist-info/METADATA
Topsis_saksham_102103521-1.1.0.dist-info/WHEEL
Topsis_saksham_102103521-1.1.0.dist-info/entry_points.txt
Topsis_saksham_102103521-1.1.0.dist-info/top_level.txt
Topsis_saksham_102103521-1.1.0.dist-info/RECORD
